{
    "SignUp": {
        "Heading": "Welcome",
        "Text": "Register your account",
        "FullName": "Full Name",
        "Email": "Email",
        "PhoneNumber": "Phone Number",
        "CreatePassword": "Create Password",
        "ConfirmPassword": "Confirm Password",
        "SignButton": "Sign Up",
        "AlreadyLogin": "Already have an account?",
        "LoginButton": "Log in"
    },
    "Login": {
        "Heading": "Welcome Back!",
        "Text": "Please enter your details.",
        "Email": "Email / Phone Number",
        "Password": "Password",
        "Remember": "Remember me",
        "Forgot": "Forgot Password?",
        "LoginButton": "Log in",
        "or": "or",
        "LoginOTP": "Log in with OTP",
        "Account": "Don't have an account?",
        "SignUpButton": "Sign Up"
    },
    "LoginOTP": {
        "Heading": "Login With OTP",
        "Text": "Please verify your registered phone number.",
        "PhoneNumber": "Phone number",
        "Accept": "I accept CRM privacy policy and Terms of use",
        "GetOTPButton": "Get OTP"
    },
    "GetOTP": {
        "Title":"Mobile Phone Verification",
        "Text": "Enter the 4-digit verification code that was sent to your phone number.",
        "EnterOTP": "Enter OTP",
        "VerifyButton": "Verify",
        "ResendOTPMSG": "Didn't receive code?",
        "ResendOTP": "Resend OTP",
        "Title2":"Email Verification",
        "Text2": "Enter the 4-digit verification code that was sent to your email."
    },
 
    "ForgotPassword": {
        "Text": "Don't worry! Fill in your email and we'll send you a link to reset your password.",
        "Email": "Email",
        "SendEmailButton": "Send Email",
        "BackToLogin": "Back to Login"
    },
    "CreateNewPassword": {
        "Heading": "Create new Password",
        "Text": "Enter new password",
        "NewPassword": "New Password",
        "ConfirmPassword": "Confirm Password",
        "ChangePasswordButton": "Change Password",
        "BackToLogin": "Back to Login"
    }
}